segment_annotation_manager/__init__.py
segment_annotation_manager/annotation.py
segment_annotation_manager/config.py
segment_annotation_manager/data_objects.py
segment_annotation_manager/dataset.py
segment_annotation_manager/environment.py
segment_annotation_manager/utils.py
segment_annotation_manager-0.0.10.dist-info/METADATA
segment_annotation_manager-0.0.10.dist-info/WHEEL
segment_annotation_manager-0.0.10.dist-info/licenses/LICENSE
segment_annotation_manager-0.0.10.dist-info/RECORD
